cuenimby/__init__.py
cuenimby/__main__.py
cuenimby/config.py
cuenimby/monitor.py
cuenimby/notifier.py
cuenimby/scheduler.py
cuenimby/tray.py
opencue_cuenimby-1.13.8.dist-info/METADATA
opencue_cuenimby-1.13.8.dist-info/WHEEL
opencue_cuenimby-1.13.8.dist-info/entry_points.txt
opencue_cuenimby-1.13.8.dist-info/RECORD
