Metadata-Version: 2.1
Name: opencue_cuenimby
Version: 1.13.8
Summary: CueNIMBY is a cross-platform system tray application for OpenCue NIMBY control. It allows workstation users to monitor their machine's rendering availability, toggle between available and disabled states, receive notifications when jobs start, and schedule automatic state changes based on time of day.
Project-URL: Homepage, https://opencue.io
Project-URL: Documentation, https://opencue.io/docs
Project-URL: Repository, https://github.com/AcademySoftwareFoundation/OpenCue
Project-URL: Issues, https://github.com/AcademySoftwareFoundation/OpenCue/issues
Author: OpenCue Contributors
License: Apache-2.0
Classifier: Development Status :: 4 - Beta
Classifier: Intended Audience :: Developers
Classifier: Intended Audience :: End Users/Desktop
Classifier: License :: OSI Approved :: Apache Software License
Classifier: Operating System :: OS Independent
Classifier: Programming Language :: Python :: 3
Classifier: Programming Language :: Python :: 3.7
Classifier: Programming Language :: Python :: 3.8
Classifier: Programming Language :: Python :: 3.9
Classifier: Programming Language :: Python :: 3.10
Classifier: Programming Language :: Python :: 3.11
Classifier: Programming Language :: Python :: 3.12
Classifier: Topic :: Multimedia :: Graphics :: 3D Rendering
Requires-Python: >=3.7
Requires-Dist: notify2>=0.3.1; sys_platform == 'linux'
Requires-Dist: opencue-pycue
Requires-Dist: pillow>=8.0.0
Requires-Dist: pync>=2.0.3; sys_platform == 'darwin'
Requires-Dist: pystray>=0.19.5
Requires-Dist: win10toast>=0.9; sys_platform == 'win32'
Provides-Extra: dev
Requires-Dist: black>=22.0; extra == 'dev'
Requires-Dist: pylint>=2.0; extra == 'dev'
Provides-Extra: test
Requires-Dist: pytest-mock>=3.0; extra == 'test'
Requires-Dist: pytest>=6.0; extra == 'test'
